audio_plot/__init__.py
audio_plot/frontend/build/asset-manifest.json
audio_plot/frontend/build/bootstrap.min.css
audio_plot/frontend/build/index.html
audio_plot/frontend/build/static/js/main.f700550a.js
audio_plot/frontend/build/static/js/main.f700550a.js.LICENSE.txt
audio_plot/frontend/build/static/js/main.f700550a.js.map
streamlit_audio_plot-0.1.1.dist-info/LICENSE
streamlit_audio_plot-0.1.1.dist-info/METADATA
streamlit_audio_plot-0.1.1.dist-info/WHEEL
streamlit_audio_plot-0.1.1.dist-info/top_level.txt
streamlit_audio_plot-0.1.1.dist-info/RECORD
