Metadata-Version: 2.1
Name: streamlit-audio-plot
Version: 0.1.1
Summary: Streamlit component that allows you to do plot audio embeddings as a plotly figure with source audio playback on hover or click.
Home-page: https://github.com/philtgun/streamlit-audio-plot
Author: Philip Tovstogan
Author-email: phil.tovstogan@gmail.com
Requires-Python: >=3.8
License-File: LICENSE
Requires-Dist: streamlit >=0.63
